duplauth/__init__.py
duplauth-0.0.1.dist-info/METADATA
duplauth-0.0.1.dist-info/WHEEL
duplauth-0.0.1.dist-info/top_level.txt
duplauth-0.0.1.dist-info/RECORD
